scylla/__init__.py
scylla/__main__.py
scylla/_version.py
scylla/cli.py
scylla/config.py
scylla/database.py
scylla/jobs.py
scylla/loggings.py
scylla/proxy_check_services.py
scylla/scheduler.py
scylla/tcpping.py
scylla/validation_policy.py
scylla/validator.py
scylla/worker.py
scylla/assets/favicon.c533504f.ico
scylla/assets/index.html
scylla/assets/scylla_banner.8d51f6c4.png
scylla/assets/src.85c0974f.css
scylla/assets/src.85c0974f.css.map
scylla/assets/src.cd388ff0.js
scylla/assets/src.cd388ff0.js.map
scylla/providers/__init__.py
scylla/providers/a2u_provider.py
scylla/providers/base_provider.py
scylla/providers/comp0_provider.py
scylla/providers/cool_proxy_provider.py
scylla/providers/data5u_provider.py
scylla/providers/free_proxy_list_provider.py
scylla/providers/http_proxy_provider.py
scylla/providers/ipaddress_provider.py
scylla/providers/kuaidaili_provider.py
scylla/providers/plain_text_provider.py
scylla/providers/proxy_list_provider.py
scylla/providers/proxy_scraper_provider.py
scylla/providers/proxylists_provider.py
scylla/providers/proxynova_provider.py
scylla/providers/pubproxy_provider.py
scylla/providers/rmccurdy_provider.py
scylla/providers/rudnkh_provider.py
scylla/providers/spys_me_provider.py
scylla/providers/spys_one_provider.py
scylla/providers/the_speedX_provider.py
scylla/providers/xici_provider.py
scylla/proxy/__init__.py
scylla/proxy/server.py
scylla/web/__init__.py
scylla/web/server.py
scylla-1.1.7.dist-info/DESCRIPTION.rst
scylla-1.1.7.dist-info/LICENSE.txt
scylla-1.1.7.dist-info/METADATA
scylla-1.1.7.dist-info/RECORD
scylla-1.1.7.dist-info/WHEEL
scylla-1.1.7.dist-info/entry_points.txt
scylla-1.1.7.dist-info/metadata.json
scylla-1.1.7.dist-info/top_level.txt
