Metadata-Version: 2.0
Name: scylla
Version: 1.1.7
Summary: Intelligent proxy pool for Humans™
Home-page: https://github.com/imWildCat/scylla
Author: WildCat
Author-email: wildcat.name@gmail.com
License: UNKNOWN
Keywords: proxy,api,scylla
Platform: UNKNOWN
Classifier: Programming Language :: Python
Classifier: Programming Language :: Python :: 3.6
Classifier: Programming Language :: Python :: Implementation :: CPython
Classifier: Programming Language :: Python :: Implementation :: PyPy
Classifier: License :: OSI Approved :: Apache Software License
Requires-Python: >=3.6.0
Requires-Dist: peewee (==3.2.2)
Requires-Dist: pycurl (==7.43.0.1)
Requires-Dist: pyppeteer (==0.0.25)
Requires-Dist: requests (==2.22.0)
Requires-Dist: requests-html (==0.9.0)
Requires-Dist: sanic (==19.6.3)
Requires-Dist: sanic-cors (==0.9.9)
Requires-Dist: schedule (==0.5.0)
Requires-Dist: six (==1.11.0)
Requires-Dist: tornado (==5.0.2)
